[
  {
    "line": 1,
    "elements": [
      {
        "before": [
          {
            "result": {
              "duration": 21194583500,
              "status": "passed"
            },
            "match": {
              "location": "Hooks.openBrowser()"
            }
          }
        ],
        "line": 5,
        "name": "Verify user should navigate to Flight Page",
        "description": "",
        "id": "flight-destination-and-search-flight-functionality;verify-user-should-navigate-to-flight-page",
        "after": [
          {
            "result": {
              "duration": 188200,
              "status": "passed"
            },
            "match": {
              "location": "Hooks.tearDown(Scenario)"
            }
          }
        ],
        "type": "scenario",
        "keyword": "Scenario",
        "steps": [
          {
            "result": {
              "duration": 569325300,
              "status": "passed"
            },
            "line": 6,
            "name": "I am on home page of expedia website",
            "match": {
              "location": "DestinationTest.iAmOnHomePageOfExpediaWebsite()"
            },
            "keyword": "Given "
          },
          {
            "result": {
              "duration": 3609006800,
              "status": "passed"
            },
            "line": 7,
            "name": "I click on Flight button",
            "match": {
              "location": "DestinationTest.iClickOnFlightButton()"
            },
            "keyword": "When "
          },
          {
            "result": {
              "duration": 506571800,
              "status": "passed"
            },
            "line": 8,
            "name": "I should navigate to Flight page successfully",
            "match": {
              "location": "DestinationTest.iShouldNavigateToFlightPageSuccessfully()"
            },
            "keyword": "Then "
          }
        ]
      },
      {
        "before": [
          {
            "result": {
              "duration": 18367212500,
              "status": "passed"
            },
            "match": {
              "location": "Hooks.openBrowser()"
            }
          }
        ],
        "line": 26,
        "name": "Verify user should find destination according there choice",
        "description": "",
        "id": "flight-destination-and-search-flight-functionality;verify-user-should-find-destination-according-there-choice;;2",
        "after": [
          {
            "result": {
              "duration": 6956601100,
              "status": "passed"
            },
            "match": {
              "location": "Hooks.tearDown(Scenario)"
            }
          }
        ],
        "type": "scenario",
        "keyword": "Scenario Outline",
        "steps": [
          {
            "result": {
              "duration": 31000,
              "status": "passed"
            },
            "line": 12,
            "name": "I am on home page of expedia website",
            "match": {
              "location": "DestinationTest.iAmOnHomePageOfExpediaWebsite()"
            },
            "keyword": "Given "
          },
          {
            "result": {
              "duration": 399227000,
              "status": "passed"
            },
            "line": 13,
            "name": "I click on Accept button",
            "match": {
              "location": "DestinationTest.iClickOnAcceptButton()"
            },
            "keyword": "And "
          },
          {
            "result": {
              "duration": 529191300,
              "status": "passed"
            },
            "line": 14,
            "name": "I click on Flight tab",
            "match": {
              "location": "DestinationTest.iClickOnFlightTab()"
            },
            "keyword": "When "
          },
          {
            "result": {
              "duration": 1319609700,
              "status": "passed"
            },
            "line": 15,
            "name": "I select flying from \"Chicago\"",
            "match": {
              "arguments": [
                {
                  "val": "Chicago",
                  "offset": 22
                }
              ],
              "location": "DestinationTest.iSelectFlyingFrom(String)"
            },
            "matchedColumns": [
              0
            ],
            "keyword": "And "
          },
          {
            "result": {
              "duration": 517837200,
              "status": "passed"
            },
            "line": 16,
            "name": "I select Going to \"Madras\"",
            "match": {
              "arguments": [
                {
                  "val": "Madras",
                  "offset": 19
                }
              ],
              "location": "DestinationTest.iSelectGoingTo(String)"
            },
            "matchedColumns": [
              1
            ],
            "keyword": "And "
          },
          {
            "result": {
              "duration": 752893800,
              "status": "passed"
            },
            "line": 17,
            "name": "I select Departing date \"15/10/2020\"",
            "match": {
              "arguments": [
                {
                  "val": "15/10/2020",
                  "offset": 25
                }
              ],
              "location": "DestinationTest.iSelectDepartingDate(String)"
            },
            "matchedColumns": [
              2
            ],
            "keyword": "And "
          },
          {
            "result": {
              "duration": 1378035800,
              "status": "passed"
            },
            "line": 18,
            "name": "I select Returning date \"21/10/2020\"",
            "match": {
              "arguments": [
                {
                  "val": "21/10/2020",
                  "offset": 25
                }
              ],
              "location": "DestinationTest.iSelectReturningDate(String)"
            },
            "matchedColumns": [
              3
            ],
            "keyword": "And "
          },
          {
            "result": {
              "duration": 324530800,
              "status": "passed"
            },
            "line": 19,
            "name": "I click on Travellers",
            "match": {
              "location": "DestinationTest.iClickOnTravellers()"
            },
            "keyword": "And "
          },
          {
            "result": {
              "duration": 292895200,
              "status": "passed"
            },
            "line": 20,
            "name": "I select two Travellers",
            "match": {
              "location": "DestinationTest.iSelectTwoTravellers()"
            },
            "keyword": "And "
          },
          {
            "result": {
              "duration": 10459962200,
              "status": "passed"
            },
            "line": 21,
            "name": "I click on close button after selection of passengers",
            "match": {
              "location": "DestinationTest.iClickOnCloseButtonAfterSelectionOfPassengers()"
            },
            "keyword": "And "
          },
          {
            "result": {
              "duration": 15619296700,
              "status": "passed"
            },
            "line": 22,
            "name": "I click on search button",
            "match": {
              "location": "DestinationTest.iClickOnSearchButton()"
            },
            "keyword": "And "
          },
          {
            "result": {
              "duration": 1443249100,
              "error_message": "org.junit.ComparisonFailure: expected:\u003c...t your departure to [Chennai]\u003e but was:\u003c...t your departure to [Madras]\u003e\r\n\tat org.junit.Assert.assertEquals(Assert.java:115)\r\n\tat org.junit.Assert.assertEquals(Assert.java:144)\r\n\tat uk.co.expedia.cucumber.stepdeps.DestinationTest.iShouldSeeMySelectedSuccessfully(DestinationTest.java:84)\r\n\tat ✽.Then I should see my selected \"Select your departure to Madras\" successfully(src/test/java/uk/co/expedia/resources/featurefile/Journey.feature:23)\r\n",
              "status": "failed"
            },
            "line": 23,
            "name": "I should see my selected \"Select your departure to Madras\" successfully",
            "match": {
              "arguments": [
                {
                  "val": "Select your departure to Madras",
                  "offset": 26
                }
              ],
              "location": "DestinationTest.iShouldSeeMySelectedSuccessfully(String)"
            },
            "matchedColumns": [
              4
            ],
            "keyword": "Then "
          }
        ]
      },
      {
        "before": [
          {
            "result": {
              "duration": 17502020900,
              "status": "passed"
            },
            "match": {
              "location": "Hooks.openBrowser()"
            }
          }
        ],
        "line": 27,
        "name": "Verify user should find destination according there choice",
        "description": "",
        "id": "flight-destination-and-search-flight-functionality;verify-user-should-find-destination-according-there-choice;;3",
        "after": [
          {
            "result": {
              "duration": 57600,
              "status": "passed"
            },
            "match": {
              "location": "Hooks.tearDown(Scenario)"
            }
          }
        ],
        "type": "scenario",
        "keyword": "Scenario Outline",
        "steps": [
          {
            "result": {
              "duration": 33100,
              "status": "passed"
            },
            "line": 12,
            "name": "I am on home page of expedia website",
            "match": {
              "location": "DestinationTest.iAmOnHomePageOfExpediaWebsite()"
            },
            "keyword": "Given "
          },
          {
            "result": {
              "duration": 247247700,
              "status": "passed"
            },
            "line": 13,
            "name": "I click on Accept button",
            "match": {
              "location": "DestinationTest.iClickOnAcceptButton()"
            },
            "keyword": "And "
          },
          {
            "result": {
              "duration": 550585900,
              "status": "passed"
            },
            "line": 14,
            "name": "I click on Flight tab",
            "match": {
              "location": "DestinationTest.iClickOnFlightTab()"
            },
            "keyword": "When "
          },
          {
            "result": {
              "duration": 1020678500,
              "status": "passed"
            },
            "line": 15,
            "name": "I select flying from \"Perth\"",
            "match": {
              "arguments": [
                {
                  "val": "Perth",
                  "offset": 22
                }
              ],
              "location": "DestinationTest.iSelectFlyingFrom(String)"
            },
            "matchedColumns": [
              0
            ],
            "keyword": "And "
          },
          {
            "result": {
              "duration": 1003717200,
              "status": "passed"
            },
            "line": 16,
            "name": "I select Going to \"Vancouver\"",
            "match": {
              "arguments": [
                {
                  "val": "Vancouver",
                  "offset": 19
                }
              ],
              "location": "DestinationTest.iSelectGoingTo(String)"
            },
            "matchedColumns": [
              1
            ],
            "keyword": "And "
          },
          {
            "result": {
              "duration": 779387200,
              "status": "passed"
            },
            "line": 17,
            "name": "I select Departing date \"17/08/2020\"",
            "match": {
              "arguments": [
                {
                  "val": "17/08/2020",
                  "offset": 25
                }
              ],
              "location": "DestinationTest.iSelectDepartingDate(String)"
            },
            "matchedColumns": [
              2
            ],
            "keyword": "And "
          },
          {
            "result": {
              "duration": 837620000,
              "status": "passed"
            },
            "line": 18,
            "name": "I select Returning date \"26/08/2020\"",
            "match": {
              "arguments": [
                {
                  "val": "26/08/2020",
                  "offset": 25
                }
              ],
              "location": "DestinationTest.iSelectReturningDate(String)"
            },
            "matchedColumns": [
              3
            ],
            "keyword": "And "
          },
          {
            "result": {
              "duration": 285605400,
              "status": "passed"
            },
            "line": 19,
            "name": "I click on Travellers",
            "match": {
              "location": "DestinationTest.iClickOnTravellers()"
            },
            "keyword": "And "
          },
          {
            "result": {
              "duration": 262099000,
              "status": "passed"
            },
            "line": 20,
            "name": "I select two Travellers",
            "match": {
              "location": "DestinationTest.iSelectTwoTravellers()"
            },
            "keyword": "And "
          },
          {
            "result": {
              "duration": 10257777400,
              "status": "passed"
            },
            "line": 21,
            "name": "I click on close button after selection of passengers",
            "match": {
              "location": "DestinationTest.iClickOnCloseButtonAfterSelectionOfPassengers()"
            },
            "keyword": "And "
          },
          {
            "result": {
              "duration": 15066234200,
              "status": "passed"
            },
            "line": 22,
            "name": "I click on search button",
            "match": {
              "location": "DestinationTest.iClickOnSearchButton()"
            },
            "keyword": "And "
          },
          {
            "result": {
              "duration": 204991800,
              "status": "passed"
            },
            "line": 23,
            "name": "I should see my selected \"Select your departure to Vancouver\" successfully",
            "match": {
              "arguments": [
                {
                  "val": "Select your departure to Vancouver",
                  "offset": 26
                }
              ],
              "location": "DestinationTest.iShouldSeeMySelectedSuccessfully(String)"
            },
            "matchedColumns": [
              4
            ],
            "keyword": "Then "
          }
        ]
      },
      {
        "before": [
          {
            "result": {
              "duration": 18332734400,
              "status": "passed"
            },
            "match": {
              "location": "Hooks.openBrowser()"
            }
          }
        ],
        "line": 28,
        "name": "Verify user should find destination according there choice",
        "description": "",
        "id": "flight-destination-and-search-flight-functionality;verify-user-should-find-destination-according-there-choice;;4",
        "after": [
          {
            "result": {
              "duration": 7102179900,
              "status": "passed"
            },
            "match": {
              "location": "Hooks.tearDown(Scenario)"
            }
          }
        ],
        "type": "scenario",
        "keyword": "Scenario Outline",
        "steps": [
          {
            "result": {
              "duration": 42000,
              "status": "passed"
            },
            "line": 12,
            "name": "I am on home page of expedia website",
            "match": {
              "location": "DestinationTest.iAmOnHomePageOfExpediaWebsite()"
            },
            "keyword": "Given "
          },
          {
            "result": {
              "duration": 688424500,
              "status": "passed"
            },
            "line": 13,
            "name": "I click on Accept button",
            "match": {
              "location": "DestinationTest.iClickOnAcceptButton()"
            },
            "keyword": "And "
          },
          {
            "result": {
              "duration": 553550000,
              "status": "passed"
            },
            "line": 14,
            "name": "I click on Flight tab",
            "match": {
              "location": "DestinationTest.iClickOnFlightTab()"
            },
            "keyword": "When "
          },
          {
            "result": {
              "duration": 1192016000,
              "status": "passed"
            },
            "line": 15,
            "name": "I select flying from \"NewYork\"",
            "match": {
              "arguments": [
                {
                  "val": "NewYork",
                  "offset": 22
                }
              ],
              "location": "DestinationTest.iSelectFlyingFrom(String)"
            },
            "matchedColumns": [
              0
            ],
            "keyword": "And "
          },
          {
            "result": {
              "duration": 577106800,
              "status": "passed"
            },
            "line": 16,
            "name": "I select Going to \"Kerala\"",
            "match": {
              "arguments": [
                {
                  "val": "Kerala",
                  "offset": 19
                }
              ],
              "location": "DestinationTest.iSelectGoingTo(String)"
            },
            "matchedColumns": [
              1
            ],
            "keyword": "And "
          },
          {
            "result": {
              "duration": 891332700,
              "status": "passed"
            },
            "line": 17,
            "name": "I select Departing date \"04/09/2020\"",
            "match": {
              "arguments": [
                {
                  "val": "04/09/2020",
                  "offset": 25
                }
              ],
              "location": "DestinationTest.iSelectDepartingDate(String)"
            },
            "matchedColumns": [
              2
            ],
            "keyword": "And "
          },
          {
            "result": {
              "duration": 1027219000,
              "status": "passed"
            },
            "line": 18,
            "name": "I select Returning date \"10/09/2020\"",
            "match": {
              "arguments": [
                {
                  "val": "10/09/2020",
                  "offset": 25
                }
              ],
              "location": "DestinationTest.iSelectReturningDate(String)"
            },
            "matchedColumns": [
              3
            ],
            "keyword": "And "
          },
          {
            "result": {
              "duration": 305425900,
              "status": "passed"
            },
            "line": 19,
            "name": "I click on Travellers",
            "match": {
              "location": "DestinationTest.iClickOnTravellers()"
            },
            "keyword": "And "
          },
          {
            "result": {
              "duration": 385216500,
              "status": "passed"
            },
            "line": 20,
            "name": "I select two Travellers",
            "match": {
              "location": "DestinationTest.iSelectTwoTravellers()"
            },
            "keyword": "And "
          },
          {
            "result": {
              "duration": 10330326800,
              "status": "passed"
            },
            "line": 21,
            "name": "I click on close button after selection of passengers",
            "match": {
              "location": "DestinationTest.iClickOnCloseButtonAfterSelectionOfPassengers()"
            },
            "keyword": "And "
          },
          {
            "result": {
              "duration": 13252974600,
              "status": "passed"
            },
            "line": 22,
            "name": "I click on search button",
            "match": {
              "location": "DestinationTest.iClickOnSearchButton()"
            },
            "keyword": "And "
          },
          {
            "result": {
              "duration": 169634100,
              "error_message": "org.junit.ComparisonFailure: expected:\u003c... your departure to K[ochi]\u003e but was:\u003c... your departure to K[erala]\u003e\r\n\tat org.junit.Assert.assertEquals(Assert.java:115)\r\n\tat org.junit.Assert.assertEquals(Assert.java:144)\r\n\tat uk.co.expedia.cucumber.stepdeps.DestinationTest.iShouldSeeMySelectedSuccessfully(DestinationTest.java:84)\r\n\tat ✽.Then I should see my selected \"Select your departure to Kerala\" successfully(src/test/java/uk/co/expedia/resources/featurefile/Journey.feature:23)\r\n",
              "status": "failed"
            },
            "line": 23,
            "name": "I should see my selected \"Select your departure to Kerala\" successfully",
            "match": {
              "arguments": [
                {
                  "val": "Select your departure to Kerala",
                  "offset": 26
                }
              ],
              "location": "DestinationTest.iShouldSeeMySelectedSuccessfully(String)"
            },
            "matchedColumns": [
              4
            ],
            "keyword": "Then "
          }
        ]
      }
    ],
    "name": "Flight Destination and Search Flight Functionality",
    "description": "As a User I want to visit \u0027expedia\u0027 website for  book flight ticket\r\nthen  I can travel according to my  choice of destination",
    "id": "flight-destination-and-search-flight-functionality",
    "keyword": "Feature",
    "uri": "src/test/java/uk/co/expedia/resources/featurefile/Journey.feature"
  },
  {
    "line": 1,
    "elements": [
      {
        "before": [
          {
            "result": {
              "duration": 18282109200,
              "status": "passed"
            },
            "match": {
              "location": "Hooks.openBrowser()"
            }
          }
        ],
        "line": 5,
        "name": "Verify User should navigate to sign in page",
        "description": "",
        "id": "login-functionality;verify-user-should-navigate-to-sign-in-page",
        "after": [
          {
            "result": {
              "duration": 44500,
              "status": "passed"
            },
            "match": {
              "location": "Hooks.tearDown(Scenario)"
            }
          }
        ],
        "type": "scenario",
        "keyword": "Scenario",
        "steps": [
          {
            "result": {
              "duration": 41000,
              "status": "passed"
            },
            "line": 6,
            "name": "I am on home page of expedia website",
            "match": {
              "location": "DestinationTest.iAmOnHomePageOfExpediaWebsite()"
            },
            "keyword": "Given "
          },
          {
            "result": {
              "duration": 429665300,
              "status": "passed"
            },
            "line": 7,
            "name": "I click on Accept button",
            "match": {
              "location": "DestinationTest.iClickOnAcceptButton()"
            },
            "keyword": "And "
          },
          {
            "result": {
              "duration": 869449300,
              "status": "passed"
            },
            "line": 8,
            "name": "I click on account button",
            "match": {
              "location": "LoginTest.iClickOnAccountButton()"
            },
            "keyword": "And "
          },
          {
            "result": {
              "duration": 615582700,
              "status": "passed"
            },
            "line": 9,
            "name": "I click on sign in button",
            "match": {
              "location": "LoginTest.iClickOnSignInButton()"
            },
            "keyword": "When "
          },
          {
            "result": {
              "duration": 507427500,
              "status": "passed"
            },
            "line": 10,
            "name": "I should be in sign in page successfully",
            "match": {
              "location": "LoginTest.iShouldBeInSignInPageSuccessfully()"
            },
            "keyword": "Then "
          }
        ]
      },
      {
        "before": [
          {
            "result": {
              "duration": 20904655200,
              "status": "passed"
            },
            "match": {
              "location": "Hooks.openBrowser()"
            }
          }
        ],
        "line": 12,
        "name": "Verify user should not login with invalid credentials",
        "description": "",
        "id": "login-functionality;verify-user-should-not-login-with-invalid-credentials",
        "after": [
          {
            "result": {
              "duration": 55100,
              "status": "passed"
            },
            "match": {
              "location": "Hooks.tearDown(Scenario)"
            }
          }
        ],
        "type": "scenario",
        "keyword": "Scenario",
        "steps": [
          {
            "result": {
              "duration": 64700,
              "status": "passed"
            },
            "line": 13,
            "name": "I am on home page of expedia website",
            "match": {
              "location": "DestinationTest.iAmOnHomePageOfExpediaWebsite()"
            },
            "keyword": "Given "
          },
          {
            "result": {
              "duration": 882292500,
              "status": "passed"
            },
            "line": 14,
            "name": "I click on Accept button",
            "match": {
              "location": "DestinationTest.iClickOnAcceptButton()"
            },
            "keyword": "And "
          },
          {
            "result": {
              "duration": 239326800,
              "status": "passed"
            },
            "line": 15,
            "name": "I click on account button",
            "match": {
              "location": "LoginTest.iClickOnAccountButton()"
            },
            "keyword": "And "
          },
          {
            "result": {
              "duration": 386943500,
              "status": "passed"
            },
            "line": 16,
            "name": "I click on sign in button",
            "match": {
              "location": "LoginTest.iClickOnSignInButton()"
            },
            "keyword": "And "
          },
          {
            "result": {
              "duration": 1981604000,
              "status": "passed"
            },
            "line": 17,
            "name": "I enter email in email field \"mittulpattel@gmail.com\"",
            "match": {
              "arguments": [
                {
                  "val": "mittulpattel@gmail.com",
                  "offset": 30
                }
              ],
              "location": "LoginTest.iEnterEmailInEmailField(String)"
            },
            "keyword": "When "
          },
          {
            "result": {
              "duration": 430129200,
              "status": "passed"
            },
            "line": 18,
            "name": "I enter password in password field \"prem1906@\"",
            "match": {
              "arguments": [
                {
                  "val": "prem1906@",
                  "offset": 36
                }
              ],
              "location": "LoginTest.iEnterPasswordInPasswordField(String)"
            },
            "keyword": "And "
          },
          {
            "result": {
              "duration": 332120800,
              "status": "passed"
            },
            "line": 19,
            "name": "I click on sign in tab",
            "match": {
              "location": "LoginTest.iClickOnSignInTab()"
            },
            "keyword": "And "
          },
          {
            "result": {
              "duration": 16796585500,
              "status": "passed"
            },
            "line": 20,
            "name": "I should see system showing error message",
            "match": {
              "location": "LoginTest.iShouldSeeSystemShowingErrorMessage()"
            },
            "keyword": "Then "
          }
        ]
      }
    ],
    "name": "Login Functionality",
    "description": "As a User I want to visit expedia website",
    "id": "login-functionality",
    "keyword": "Feature",
    "uri": "src/test/java/uk/co/expedia/resources/featurefile/login.feature"
  }
]